[{
  "_id": {
    "$oid": "61aa22022cb3c73f19181ef6"
  },
  "body": "Lorem ipsum dolor sit amet.",
  "deleted": false
},{
  "_id": {
    "$oid": "61aa222f2cb3c73f19181ef7"
  },
  "parent_id": {
    "$oid": "61aa22022cb3c73f19181ef6"
  },
  "body": "Donec commodo odio ut cursus luctus.",
  "created_at": {
    "$date": "2021-01-02T22:00:00Z"
  },
  "deleted": false
},{
  "_id": {
    "$oid": "61aa228a2cb3c73f19181ef9"
  },
  "body": "Donec sed tortor in urna commodo consectetur rhoncus in quam.",
  "parent_id": {
    "$oid": "61aa22022cb3c73f19181ef6"
  },
  "created_at": {
    "$date": "2021-01-03T22:00:00Z"
  },
  "deleted": false
},{
  "_id": {
    "$oid": "61aa22bc2cb3c73f19181efb"
  },
  "body": "Integer accumsan turpis id nibh ultricies ullamcorper.",
  "parent_id": {
    "$oid": "61aa22022cb3c73f19181ef6"
  },
  "created_at": {
    "$date": "2021-01-04T22:00:00Z"
  },
  "deleted": false
},{
  "_id": {
    "$oid": "61aa22ff2cb3c73f19181efc"
  },
  "body": "Duis ac lacus imperdiet, cursus sem quis, commodo erat.",
  "parent_id": {
    "$oid": "61aa22022cb3c73f19181ef6"
  },
  "created_at": {
    "$date": "2021-01-06T22:00:00Z"
  },
  "deleted": false
},{
  "_id": {
    "$oid": "61aa23222cb3c73f19181efd"
  },
  "body": "Vestibulum quis lacus vitae est lacinia posuere.",
  "parent_id": {
    "$iod": "61aa22022cb3c73f19181ef6"
  },
  "created_at": {
    "$date": "2021-02-02T22:00:00Z"
  },
  "delted": false
},{
  "_id": {
    "$oid": "61aa237c2cb3c73f19181efe"
  },
  "parent_id": {
    "$oid": "61aa22022cb3c73f19181ef6"
  },
  "body": "Cras a ligula ac ligula gravida aliquam vitae quis nisl.",
  "created_at": {
    "$date": "2021-02-03T22:00:00Z"
  },
  "deleted": false
},{
  "_id": {
    "$oid": "61aa23ae2cb3c73f19181eff"
  },
  "parent_id": {
    "$oid": "61aa22022cb3c73f19181ef6"
  },
  "body": "Etiam varius ipsum aliquet, consequat erat ut, commodo nunc.",
  "created_at": {
    "$date": "2021-02-10T22:00:00Z"
  },
  "deleted": false
},{
  "_id": {
    "$oid": "61aa23cd2cb3c73f19181f00"
  },
  "parent_id": {
    "$oid": "61aa23ae2cb3c73f19181eff"
  },
  "body": "Maecenas quis erat vel lectus porta fermentum sed ac nulla.",
  "created_at": {
    "$date": "2021-11-12T22:00:00Z"
  },
  "deleted": false
},{
  "_id": {
    "$oid": "61aa23f02cb3c73f19181f01"
  },
  "parent_id": {
    "$oid": "61aa23ae2cb3c73f19181eff"
  },
  "body": "Quisque faucibus leo non dolor dapibus, in semper ex fermentum.",
  "created_at": {
    "$date": "2021-11-02T22:00:00Z"
  },
  "deleted": false
},{
  "_id": {
    "$oid": "61aa24192cb3c73f19181f02"
  },
  "parent_id": {
    "$oid": "61aa23f02cb3c73f19181f01"
  },
  "body": "Nunc molestie leo a elit bibendum commodo.",
  "created_at": {
    "$date": "2021-10-20T22:00:00Z"
  },
  "deleted": false
},{
  "_id": {
    "$oid": "61aa243e2cb3c73f19181f04"
  },
  "parent_id": {
    "$oid": "61aa24192cb3c73f19181f02"
  },
  "body": "Donec lacinia velit ac est interdum, ac accumsan nulla volutpat.",
  "created_at": {
    "$date": "2021-12-12T22:00:00Z"
  },
  "deleted": false
},{
  "_id": {
    "$oid": "61aa24552cb3c73f19181f05"
  },
  "parent_id": {
    "$oid": "61aa243e2cb3c73f19181f04"
  },
  "body": "Donec vitae mi et urna sollicitudin scelerisque.",
  "created_at": {
    "$date": "2021-12-15T22:00:00Z"
  },
  "deleted": false
}]